lgl/__init__.py
lgl/get_unresolve.py
lgl/init.py
lgl/lgl.py
lgl/run.py
lgl/traverse.py
lgl-0.1.3.dist-info/DESCRIPTION.rst
lgl-0.1.3.dist-info/METADATA
lgl-0.1.3.dist-info/RECORD
lgl-0.1.3.dist-info/WHEEL
lgl-0.1.3.dist-info/entry_points.txt
lgl-0.1.3.dist-info/metadata.json
lgl-0.1.3.dist-info/top_level.txt
