Metadata-Version: 2.0
Name: lgl
Version: 0.1.3
Summary: launch python.
Home-page: https://github.com/libgirlenterprise/lgl
Author: Team Libgirl
Author-email: team@libgirl.com
License: Apache License 2.0
Platform: UNKNOWN
Classifier: Development Status :: 4 - Beta
Classifier: Intended Audience :: Developers
Classifier: License :: OSI Approved :: Apache Software License
Classifier: Programming Language :: Python
Classifier: Programming Language :: Python :: 3
Classifier: Topic :: Utilities
Requires-Dist: toml
Requires-Dist: importmagic
